<?xml version="1.0" encoding="utf-8"?>
<ModMetaData>
  <name>Industrial Age - Objects and Furniture (Continued)</name>
  <packageId>Mlie.CallofCthulhuIndustrialAge</packageId>
  <author>jecrell</author>
  <url>https://github.com/emipa606/CallofCthulhuIndustrialAge</url>
  <supportedVersions>
    <li>1.0</li>
    <li>1.1</li>
    <li>1.2</li>
  </supportedVersions>
  <modDependencies>
    <li>
      <packageId>jecrell.jecstools</packageId>
      <displayName>JecsTools</displayName>
      <steamWorkshopUrl>steam://url/CommunityFilePage/2195729899</steamWorkshopUrl>
    </li>
  </modDependencies>
  <loadAfter>
    <li>jecrell.jecstools</li>
  </loadAfter>
  <description>Update of jecrells mod
https://steamcommunity.com/sharedfiles/filedetails/?id=777197241

[img]https://i.imgur.com/GYswkZ7.png[/img]

Support-chat:
https://invite.gg/mlie

Non-steam version:
https://github.com/emipa606/CallofCthulhuIndustrialAge
	
- This is an unofficial port
- This will be removed when/if Jecrell comes back

--- Original Description ---
Adds new furniture and appliances to your game from the time period of the late 1800's and early 1900s themed after the industrial era.

Adds the following objects:
Refrigerator - Stores meals and freezes them.
Telegraph- Lets colonists use a communicator at an earlier tech level.
Gramophone - Plays music for your old timey colonists.
Wood Stove Furnace - Pushes heat and lets you cook without electricity.
Candelabra
Chandelier
Grand chandelier
Street Gas Lamp
Interior Gas Lamp
Tesla arc lamp
Edison lamp
Edison tube
Books and bookcases have been moved to a new mod: RimWriter!
https://ludeon.com/forums/index.php?topic=45847.0

Adds the following resources:
Wax (Obtained from meat at cooking tables)


Special thanks to Inverness and MrXuiryus for contributing their assets towards the creation of this Industrial Age series (yes, future mods, too!).
</description>
</ModMetaData>